taskmanager_hjy/__init__.py
taskmanager_hjy/__main__.py
taskmanager_hjy/cli.py
taskmanager_hjy/version.py
taskmanager_hjy/core/manager.py
taskmanager_hjy/core/models.py
taskmanager_hjy/core/utils.py
taskmanager_hjy-0.4.4.dist-info/LICENSE
taskmanager_hjy-0.4.4.dist-info/METADATA
taskmanager_hjy-0.4.4.dist-info/WHEEL
taskmanager_hjy-0.4.4.dist-info/entry_points.txt
taskmanager_hjy-0.4.4.dist-info/top_level.txt
taskmanager_hjy-0.4.4.dist-info/RECORD
