Metadata-Version: 2.1
Name: taskmanager-hjy
Version: 0.4.4
Summary: 完全独立的任务管理包 - 基于新包架构，无旧包依赖
Home-page: https://github.com/hjy/taskmanager-hjy
Author: hjy
Author-email: hjy@example.com
License: UNKNOWN
Platform: UNKNOWN
Classifier: Development Status :: 4 - Beta
Classifier: Intended Audience :: Developers
Classifier: License :: OSI Approved :: MIT License
Classifier: Operating System :: OS Independent
Classifier: Programming Language :: Python :: 3
Classifier: Programming Language :: Python :: 3.8
Classifier: Programming Language :: Python :: 3.9
Classifier: Programming Language :: Python :: 3.10
Classifier: Programming Language :: Python :: 3.11
Classifier: Programming Language :: Python :: 3.12
Classifier: Programming Language :: Python :: 3.13
Requires-Python: >=3.8
License-File: LICENSE
Requires-Dist: pydantic>=2.0.0
Requires-Dist: loguru>=0.7.0
Requires-Dist: redis>=4.5.0
Requires-Dist: rq>=1.15.0
Requires-Dist: pyyaml>=6.0
Requires-Dist: typing-extensions>=4.0.0
Requires-Dist: configmanager-hjy>=0.3.0
Requires-Dist: datamanager-hjy>=0.3.0
Requires-Dist: aimanager-hjy>=0.3.0
Requires-Dist: keymanager-hjy>=0.3.0
Provides-Extra: dev
Requires-Dist: pytest>=6.0; extra == "dev"
Requires-Dist: pytest-asyncio>=0.18.0; extra == "dev"
Requires-Dist: black>=22.0; extra == "dev"
Requires-Dist: isort>=5.0; extra == "dev"
